<?xml version="1.0" encoding="utf-8"?>
<opc:ModelDesign
	xmlns:xsi="http://www.w3.org/2001/XMLSchema-instance"
	xmlns:xsd="http://www.w3.org/2001/XMLSchema"
	xmlns:opc="http://opcfoundation.org/UA/ModelDesign.xsd"
  xmlns:ua="http://opcfoundation.org/UA/"
  xmlns:uax="http://opcfoundation.org/UA/2008/02/Types.xsd"
	xmlns="http://opcfoundation.org/UA/Publisher/"
  TargetNamespace="http://opcfoundation.org/UA/Publisher/"
>

  <!-- 
  This element defines the mappings between the URIs used to identify namespaces and the symbols used in code.
  User defined design files can include other user defined design files.
  The location of included design files is specified with the FilePath attribute (absolute or relative path without the .xml suffix).
  -->
  <opc:Namespaces>
    <opc:Namespace Name="OpcUa" Prefix="Opc.Ua" InternalPrefix="Opc.Ua.Server" XmlNamespace="http://opcfoundation.org/UA/2008/02/Types.xsd">http://opcfoundation.org/UA/</opc:Namespace>
    <opc:Namespace Name="Publisher" Prefix="Publisher">http://opcfoundation.org/UA/Publisher/</opc:Namespace>
  </opc:Namespaces>

  <opc:Method SymbolicName="PublishNodeMethodType" BaseType="ua:BaseObjectType">
    <opc:InputArguments>
      <opc:Argument Name="NodeID" DataType="ua:String" ValueRank="Scalar" AccessLevel="ReadWrite">
        <opc:Description>The NodeID to publish</opc:Description>
      </opc:Argument>
      <opc:Argument Name="ServerEndpointUrl" DataType="ua:String" ValueRank="Scalar" AccessLevel="ReadWrite">
        <opc:Description>The server endpoint URL to grab the node from</opc:Description>
      </opc:Argument>
    </opc:InputArguments>
  </opc:Method>

  <opc:Method SymbolicName="UnPublishNodeMethodType" BaseType="ua:BaseObjectType">
    <opc:InputArguments>
      <opc:Argument Name="NodeID" DataType="ua:String" ValueRank="Scalar" AccessLevel="ReadWrite">
        <opc:Description>The NodeID to publish</opc:Description>
      </opc:Argument>
      <opc:Argument Name="ServerEndpointUrl" DataType="ua:String" ValueRank="Scalar" AccessLevel="ReadWrite">
        <opc:Description>The server endpoint URL to grab the node from</opc:Description>
      </opc:Argument>
    </opc:InputArguments>
  </opc:Method>

  <opc:Method SymbolicName="GetListOfPublishedNodesMethodType" BaseType="ua:BaseObjectType">
    <opc:OutputArguments>
      <opc:Argument Name="NodeList" DataType="ua:String" ValueRank="Scalar" AccessLevel="ReadWrite">
        <opc:Description>The JSON-formatted node list currently being published</opc:Description>
      </opc:Argument>
    </opc:OutputArguments>
  </opc:Method>

  <opc:ObjectType SymbolicName="PublisherType" BaseType="ua:BaseObjectType" SupportsEvents="true">
    <opc:Description>Publisher</opc:Description>
    <opc:Children>
      <opc:Method SymbolicName="PublishNode" TypeDefinition="PublishNodeMethodType" />
      <opc:Method SymbolicName="UnPublishNode" TypeDefinition="UnPublishNodeMethodType" />
      <opc:Method SymbolicName="GetListOfPublishedNodes" TypeDefinition="GetListOfPublishedNodesMethodType"/>
      <opc:Variable SymbolicName="ConnectionString" DataType="ua:String" ValueRank="Scalar" AccessLevel="Write" />
    </opc:Children>
  </opc:ObjectType>

  <!-- Declare an instance of a Publisher. -->
  <opc:Object SymbolicName="PublisherInstance" TypeDefinition="PublisherType" SupportsEvents="true">
    <opc:BrowseName>PublisherInstance</opc:BrowseName>
     <!--Link the instance back to the ObjectsFolder--> 
    <opc:References>
      <opc:Reference IsInverse="true">
        <opc:ReferenceType>ua:Organizes</opc:ReferenceType>
        <opc:TargetId>ua:ObjectsFolder</opc:TargetId>
      </opc:Reference>
    </opc:References>
  </opc:Object>
  
</opc:ModelDesign>